StreamDeckLayoutManager/CallbackCall.py
StreamDeckLayoutManager/KeyConfig.py
StreamDeckLayoutManager/Manager.py
StreamDeckLayoutManager/__about__.py
StreamDeckLayoutManager/__init__.py
StreamDeckLayoutManager/py.typed
streamdecklayoutmanager-4.1.1.dist-info/METADATA
streamdecklayoutmanager-4.1.1.dist-info/WHEEL
streamdecklayoutmanager-4.1.1.dist-info/licenses/LICENSE
streamdecklayoutmanager-4.1.1.dist-info/RECORD
