Metadata-Version: 2.4
Name: StreamDeckLayoutManager
Version: 4.1.1
Summary: A higher-level Python API for ElGato's Stream Deck.
Project-URL: Source Code, https://code.malenfant.net/didier/StreamDeckLayoutManager
Project-URL: Bug Tracker, https://code.malenfant.net/didier/StreamDeckLayoutManager/issues
Author-email: Didier Malenfant <didier@malenfant.net>
License-Expression: GPL-3.0-or-later
License-File: LICENSE
Keywords: elgato,streamdeck
Classifier: Development Status :: 5 - Production/Stable
Classifier: Programming Language :: Python
Classifier: Programming Language :: Python :: Implementation :: CPython
Classifier: Programming Language :: Python :: Implementation :: PyPy
Requires-Python: >=3.8
Requires-Dist: dm-py-utilities>=2.1.0
Requires-Dist: pillow>=9.0.0
Requires-Dist: streamdeck
Requires-Dist: tomli>=1.1.0; python_version < '3.11'
